messaging_core/__init__.py
messaging_core/attachment_pb2.py
messaging_core/attachment_pb2_grpc.py
messaging_core/auth_pb2.py
messaging_core/auth_pb2_grpc.py
messaging_core/client.py
messaging_core/conversation_pb2.py
messaging_core/conversation_pb2_grpc.py
messaging_core/enums.py
messaging_core/messaging_pb2.py
messaging_core/messaging_pb2_grpc.py
messaging_core/users_pb2.py
messaging_core/users_pb2_grpc.py
messaging_core-0.1.1.dist-info/METADATA
messaging_core-0.1.1.dist-info/WHEEL
messaging_core-0.1.1.dist-info/top_level.txt
messaging_core-0.1.1.dist-info/RECORD
