Metadata-Version: 2.4
Name: messaging_core
Version: 0.1.1
Summary: Python gRPC client for Your Service
Requires-Python: >=3.8
Requires-Dist: grpcio>=1.60.0
Requires-Dist: protobuf>=4.25.0
